spaceeval/__init__.py
spaceeval/sports/__init__.py
spaceeval/sports/main_class.py
spaceeval/sports/basketball/__init__.py
spaceeval/sports/basketball/application/__init__.py
spaceeval/sports/basketball/application/heatmap.py
spaceeval/sports/basketball/main_class_basketball/__init__.py
spaceeval/sports/basketball/main_class_basketball/main.py
spaceeval/sports/basketball/model_parameter/__init__.py
spaceeval/sports/basketball/model_parameter/params.yaml
spaceeval/sports/basketball/models/BIMOS.py
spaceeval/sports/basketball/models/BMOS.py
spaceeval/sports/basketball/models/__init__.py
spaceeval/sports/basketball/utils/SportVU_IO.py
spaceeval/sports/basketball/utils/__init__.py
spaceeval/sports/basketball/utils/get_residual_param.py
spaceeval/sports/basketball/utils/id_team.csv
spaceeval/sports/basketball/utils/nba_court.png
spaceeval/sports/basketball/utils/onballevents_dataset.mat
spaceeval/sports/basketball/utils/scoremodel_basket.csv
spaceeval/sports/basketball/utils/transitionmodel.csv
spaceeval/sports/soccer/__init__.py
spaceeval/sports/soccer/soccer_main_func.py
spaceeval/sports/soccer/bimos/__init__.py
spaceeval/sports/soccer/bimos/get_bimos_value.py
spaceeval/sports/soccer/bimos/soccer_bimos_main_class.py
spaceeval/sports/soccer/bimos/vis_bimos.py
spaceeval/sports/soccer/bimos/bimos_repo/SportVU_ControlField.py
spaceeval/sports/soccer/bimos/bimos_repo/cal_pbcf.py
spaceeval/sports/soccer/bimos/c_obso_repo/Metrica_EPV.py
spaceeval/sports/soccer/bimos/c_obso_repo/Metrica_IO.py
spaceeval/sports/soccer/bimos/c_obso_repo/Metrica_PitchControl.py
spaceeval/sports/soccer/bimos/c_obso_repo/Metrica_Velocities.py
spaceeval/sports/soccer/bimos/c_obso_repo/__init__.py
spaceeval/sports/soccer/bimos/c_obso_repo/obso_player.py
spaceeval/sports/soccer/obso/__init__.py
spaceeval/sports/soccer/obso/get_obso_value.py
spaceeval/sports/soccer/obso/soccer_obso_main_class.py
spaceeval/sports/soccer/obso/vis_obso.py
spaceeval/sports/soccer/obso/c_obso_repo/EPV_grid.csv
openstarlab_spaceeval-0.0.9.dist-info/LICENSE.md
openstarlab_spaceeval-0.0.9.dist-info/METADATA
openstarlab_spaceeval-0.0.9.dist-info/WHEEL
openstarlab_spaceeval-0.0.9.dist-info/top_level.txt
openstarlab_spaceeval-0.0.9.dist-info/RECORD
