Metadata-Version: 2.1
Name: openstarlab-spaceEval
Version: 0.0.9
Summary: openstarlab space eval package
Author-email: Calvin Yeung <yeung.chikwong@g.sp.m.is.nagoya-u.ac.jp>
License: Apache License 2.0
Project-URL: Homepage, https://github.com/open-starlab/
Classifier: Programming Language :: Python :: 3
Classifier: License :: OSI Approved :: Apache Software License
Classifier: Operating System :: OS Independent
Requires-Python: >=3.8
License-File: LICENSE.md
Requires-Dist: pandas
Requires-Dist: numpy
Requires-Dist: matplotlib
Requires-Dist: scipy
Requires-Dist: tqdm
Requires-Dist: opencv-python
Requires-Dist: joblib
